{
  "id": "5",
  "created" : "2016-03-16T07:39:21.159Z",
  "bookingBy": "Snoopy Doo",
  "phoneNo": "095-000-1919",
  "lineID" : "@snoopy.doo",
  "email" : "snoopy.doo@mail.com",
  "status": 3,
  "careTaker" : 5,
  "careTakerAge": 65,
  "careTakerGender" : 1,
  "diagnosis": "Other",
  "diagnosisOther": "หัวใจล้มเหลว",
  "underlyingDisease": "ซึมเศร้า",
  "caregiverGender" : 1,
  "skills": {
    "ADL": true,
    "bedRidden": false,
    "tracheostomy": false,
    "tubeFeeding": false,
    "CAPD": true,
    "pressureSore":false
  },
  "careDuration" : "short",
  "careDates" : [
    "2016-03-31T17:00:00.000Z",
    "2016-04-02T17:00:00.000Z",
    "2016-04-03T17:00:00.000Z",
    "2016-04-04T17:00:00.000Z",
    "2016-04-05T17:00:00.000Z"
  ],
  "careTime": "12",
  "address": {
    "address": "152",
    "street": "พหลโยธิน",
    "subdistrict": "สามเสนใน",
    "district": "พญาไท",
    "province": "กรุงเทพมหานคร",
    "zip": "10400"
  },
  "note": "",
  "expired": "2016-03-19T07:20:21.159Z"
}